jabroni/__init__.py
jabroni/_version.py
jabroni/data.json
jabroni-0.0.1.dev1.dist-info/LICENSE.txt
jabroni-0.0.1.dev1.dist-info/METADATA
jabroni-0.0.1.dev1.dist-info/WHEEL
jabroni-0.0.1.dev1.dist-info/top_level.txt
jabroni-0.0.1.dev1.dist-info/RECORD
