Metadata-Version: 2.1
Name: jabroni
Version: 0.0.1.dev1
Summary: Convert between long and short journal titles.
Author-email: Remington Mallett <mallett.remy@gmail.com>
Maintainer-email: Remington Mallett <mallett.remy@gmail.com>
License: This is free and unencumbered software released into the public domain.
Project-URL: Homepage, https://github.com/remrama/jabroni
Keywords: iso4
Classifier: Development Status :: 1 - Planning
Classifier: License :: OSI Approved :: The Unlicense (Unlicense)
Classifier: Operating System :: OS Independent
Classifier: Intended Audience :: Science/Research
Classifier: Topic :: Scientific/Engineering
Classifier: Programming Language :: Python
Requires-Python: >=3.7
License-File: LICENSE.txt
